web3quorum/__init__.py
web3quorum/quorum.py
web3quorum/test_utils.py
web3quorum/utils.py
web3quorum-1.2.1.dist-info/LICENSE
web3quorum-1.2.1.dist-info/METADATA
web3quorum-1.2.1.dist-info/WHEEL
web3quorum-1.2.1.dist-info/RECORD
