Metadata-Version: 2.1
Name: web3quorum
Version: 1.2.1
Summary: A library to interact with Quorum API
License: MIT
Author: Chainstack
Author-email: dev@chainstack.com
Requires-Python: >=3.7.2,<4.0.0
Classifier: License :: OSI Approved :: MIT License
Classifier: Programming Language :: Python :: 3
Classifier: Programming Language :: Python :: 3.8
Classifier: Programming Language :: Python :: 3.9
Classifier: Programming Language :: Python :: 3.10
Classifier: Programming Language :: Python :: 3.11
Requires-Dist: web3 (>=6.0.0b9,<7.0.0)
